pydojo/__init__.py
pydojo/authenticate.py
pydojo/connect.py
pydojo/dojo.py
dojo_py-0.0.4.dist-info/LICENSE.md
dojo_py-0.0.4.dist-info/METADATA
dojo_py-0.0.4.dist-info/WHEEL
dojo_py-0.0.4.dist-info/top_level.txt
dojo_py-0.0.4.dist-info/RECORD
